tracc/__init__.py
tracc/functions.py
tracc/spatial.py
tracc/tracc.py
tracc-0.0.4.dist-info/LICENSE
tracc-0.0.4.dist-info/METADATA
tracc-0.0.4.dist-info/WHEEL
tracc-0.0.4.dist-info/top_level.txt
tracc-0.0.4.dist-info/RECORD
