Metadata-Version: 2.1
Name: tracc
Version: 0.0.4
Summary: Transport accessibility measures in Python
Home-page: https://github.com/jamaps/tracc
Author: Jeff Allen
Author-email: jeff.allen@utoronto.ca
License: UNKNOWN
Platform: UNKNOWN
Classifier: Programming Language :: Python :: 3
Classifier: License :: OSI Approved :: MIT License
Classifier: Operating System :: OS Independent
Requires-Python: >=3.6
Requires-Dist: pandas (>=1.0)
Requires-Dist: numpy (>=1.18.5)
Requires-Dist: geopandas (>=0.7.0)
Requires-Dist: libpysal (>=4.3.0)
